LICENSE
README.md
setup.py
nordicsemi/__init__.py
nordicsemi/__main__.py
nordicsemi/version.py
nordicsemi/../requirements.txt
nordicsemi/../libusb/LICENSE
nordicsemi/../libusb/x64/libusb-1.0.dll
nordicsemi/../libusb/x64/libusb-1.0.dylib
nordicsemi/../libusb/x86/libusb-1.0.dll
nordicsemi/dfu/__init__.py
nordicsemi/dfu/bl_dfu_sett.py
nordicsemi/dfu/crc16.py
nordicsemi/dfu/dfu.py
nordicsemi/dfu/dfu_cc_pb2.py
nordicsemi/dfu/dfu_transport.py
nordicsemi/dfu/dfu_transport_ant.py
nordicsemi/dfu/dfu_transport_ble.py
nordicsemi/dfu/dfu_transport_serial.py
nordicsemi/dfu/dfu_trigger.py
nordicsemi/dfu/init_packet_pb.py
nordicsemi/dfu/manifest.py
nordicsemi/dfu/model.py
nordicsemi/dfu/nrfhex.py
nordicsemi/dfu/package.py
nordicsemi/dfu/signing.py
nordicsemi/dfu/tests/__init__.py
nordicsemi/dfu/tests/test_bl_dfu_sett.py
nordicsemi/dfu/tests/test_init_packet_pb.py
nordicsemi/dfu/tests/test_manifest.py
nordicsemi/dfu/tests/test_nrfhex.py
nordicsemi/dfu/tests/test_package.py
nordicsemi/dfu/tests/test_signing.py
nordicsemi/lister/__init__.py
nordicsemi/lister/device_lister.py
nordicsemi/lister/enumerated_device.py
nordicsemi/lister/lister_backend.py
nordicsemi/lister/unix/__init__.py
nordicsemi/lister/unix/unix_lister.py
nordicsemi/lister/windows/__init__.py
nordicsemi/lister/windows/constants.py
nordicsemi/lister/windows/lister_win32.py
nordicsemi/lister/windows/structures.py
nordicsemi/thread/__init__.py
nordicsemi/thread/dfu_server.py
nordicsemi/thread/dfu_thread.py
nordicsemi/thread/ncp_flasher.py
nordicsemi/thread/tncp.py
nordicsemi/thread/hex/ncp.hex
nordicsemi/utility/__init__.py
nordicsemi/utility/target_registry.py
nordicsemi/utility/tests/__init__.py
nordicsemi/utility/tests/test_target_registry.py
nordicsemi/zigbee/__init__.py
nordicsemi/zigbee/ota_file.py
nordicsemi/zigbee/ota_flasher.py
nordicsemi/zigbee/prod_config.py
nordicsemi/zigbee/hex/ota.hex
nordicsemi/zigbee/tests/__init__.py
nordicsemi/zigbee/tests/test_prod_config.py
nrfutil.egg-info/PKG-INFO
nrfutil.egg-info/SOURCES.txt
nrfutil.egg-info/dependency_links.txt
nrfutil.egg-info/entry_points.txt
nrfutil.egg-info/not-zip-safe
nrfutil.egg-info/requires.txt
nrfutil.egg-info/top_level.txt