Metadata-Version: 2.1
Name: nrfutil
Version: 6.1.4
Summary: Nordic Semiconductor nrfutil utility and Python library
Home-page: https://github.com/NordicSemiconductor/pc-nrfutil
Author: Nordic Semiconductor ASA
License: Other/Proprietary License
Keywords: nordic nrf51 nrf52 ble bluetooth dfu ota softdevice serialization nrfutil pc-nrfutil
Classifier: Development Status :: 4 - Beta
Classifier: Intended Audience :: Developers
Classifier: Operating System :: MacOS
Classifier: Operating System :: Microsoft :: Windows
Classifier: Operating System :: POSIX :: Linux
Classifier: Topic :: System :: Networking
Classifier: Topic :: System :: Hardware :: Hardware Drivers
Classifier: Topic :: Software Development :: Embedded Systems
Classifier: License :: Other/Proprietary License
Classifier: Programming Language :: Python :: 3.7
Classifier: Programming Language :: Python :: 3.8
Classifier: Programming Language :: Python :: 3.9
Classifier: Programming Language :: Python :: 3.10
Requires-Python: >=3.7, <3.11
License-File: LICENSE
